README
setup.py
myvdl.egg-info/PKG-INFO
myvdl.egg-info/SOURCES.txt
myvdl.egg-info/dependency_links.txt
myvdl.egg-info/entry_points.txt
myvdl.egg-info/requires.txt
myvdl.egg-info/top_level.txt
myvdlclass/__init__.py
myvdlclass/version.py
myvdlclass/lib/__init__.py
myvdlclass/lib/core.py
myvdlclass/lib/curl.py
myvdlclass/lib/plugins.py
myvdlclass/plugins/__init__.py
myvdlclass/plugins/base.py
myvdlclass/plugins/mailru.py
myvdlclass/plugins/tntonline.py
myvdlclass/plugins/youtube.py
myvdlclass/plugins/rutuberu/__init__.py
myvdlclass/plugins/rutuberu/embed.py
myvdlclass/plugins/rutuberu/mainpage.py
myvdlclass/plugins/usclab/__init__.py
myvdlclass/scripts/__init__.py
myvdlclass/scripts/myvdl.py