Metadata-Version: 1.0
Name: myvdl
Version: 1.0.4
Summary: MyVDl - program for download video from ext video sevices
